[
  {
    "name": "application/vnd.lotus-1-2-3",
    "fileTypes": [
      ".123"
    ]
  },
  {
    "name": "text/vnd.in3d.3dml",
    "fileTypes": [
      ".3dml"
    ]
  },
  {
    "name": "video/3gpp2",
    "fileTypes": [
      ".3g2"
    ]
  },
  {
    "name": "image/avif",
    "fileTypes": [
      ".avif",
      ".avifs"
    ]
  },
  {
    "name": "application/x-krita",
    "fileTypes": [
      ".kra",
      ".krz"
    ]
  },
  {
    "name": "image/heic",
    "fileTypes": [
      ".heif",
      ".heic"
    ]
  },
  {
    "name": "video/3gpp",
    "fileTypes": [
      ".3gp"
    ]
  },
  {
    "name": "audio/3gpp2",
    "fileTypes": [
      ".3g2"
    ]
  },
  {
    "name": "application/x-7z-compressed",
    "fileTypes": [
      ".7z"
    ]
  },
  {
    "name": "application/octet-stream",
    "fileTypes": [
      ".a",
      ".bin",
      ".bpk",
      ".deploy",
      ".dist",
      ".distz",
      ".dmg",
      ".dms",
      ".dump",
      ".elc",
      ".lha",
      ".lrf",
      ".lzh",
      ".o",
      ".obj",
      ".pkg",
      ".so"
    ]
  },
  {
    "name": "application/x-authorware-bin",
    "fileTypes": [
      ".aab",
      ".u32",
      ".vox",
      ".x32"
    ]
  },
  {
    "name": "image/x-icns",
    "fileTypes": [
      ".icns"
    ]
  },
  {
    "name": "audio/mp4",
    "fileTypes": [
      ".mp4",
      ".m4a",
      ".m4b",
      ".m4p",
      ".m4r",
      ".m4v",
      ".mp4v",
      ".3gp",
      ".3g2",
      ".3ga",
      ".3gpa",
      ".3gpp",
      ".3gpp2",
      ".3gp2"
    ]
  },
  {
    "name": "audio/aac",
    "fileTypes": [
      ".aac",
      ".m4a"
    ]
  },
  {
    "name": "audio/mp4a-latm",
    "fileTypes": []
  },
  {
    "name": "audio/aacp",
    "fileTypes": [
      ".aacp"
    ]
  },
  {
    "name": "application/x-authorware-map",
    "fileTypes": [
      ".aam"
    ]
  },
  {
    "name": "application/x-authorware-seg",
    "fileTypes": [
      ".aas"
    ]
  },
  {
    "name": "application/x-abiword",
    "fileTypes": [
      ".abw",
      ".zabw",
      ".abw.gz"
    ]
  },
  {
    "name": "application/vnd.americandynamics.acc",
    "fileTypes": [
      ".acc"
    ]
  },
  {
    "name": "application/x-ace-compressed",
    "fileTypes": [
      ".ace"
    ]
  },
  {
    "name": "application/vnd.acucobol",
    "fileTypes": [
      ".acu"
    ]
  },
  {
    "name": "application/vnd.acucorp",
    "fileTypes": [
      ".acutc",
      ".atc"
    ]
  },
  {
    "name": "audio/adpcm",
    "fileTypes": [
      ".adp"
    ]
  },
  {
    "name": "application/vnd.audiograph",
    "fileTypes": [
      ".aep"
    ]
  },
  {
    "name": "application/x-font-type1",
    "fileTypes": [
      ".afm",
      ".pfa",
      ".pfb",
      ".pfm"
    ]
  },
  {
    "name": "application/vnd.ibm.modcap",
    "fileTypes": [
      ".afp",
      ".list3820",
      ".listafp"
    ]
  },
  {
    "name": "application/postscript",
    "fileTypes": [
      ".ai",
      ".eps",
      ".ps"
    ]
  },
  {
    "name": "application/vnd.adobe.air-application-installer-package+zip",
    "fileTypes": [
      ".air"
    ]
  },
  {
    "name": "application/vnd.amiga.ami",
    "fileTypes": [
      ".ami"
    ]
  },
  {
    "name": "application/vnd.android.package-archive",
    "fileTypes": [
      ".apk"
    ]
  },
  {
    "name": "application/x-ms-application",
    "fileTypes": [
      ".application"
    ]
  },
  {
    "name": "application/vnd.lotus-approach",
    "fileTypes": [
      ".apr"
    ]
  },
  {
    "name": "application/pgp-signature",
    "fileTypes": [
      ".asc",
      ".sig"
    ]
  },
  {
    "name": "video/x-ms-asf",
    "fileTypes": [
      ".asf",
      ".asx"
    ]
  },
  {
    "name": "text/x-asm",
    "fileTypes": [
      ".asm",
      ".s"
    ]
  },
  {
    "name": "application/vnd.accpac.simply.aso",
    "fileTypes": [
      ".aso"
    ]
  },
  {
    "name": "application/atom+xml",
    "fileTypes": [
      ".atom"
    ]
  },
  {
    "name": "application/atomcat+xml",
    "fileTypes": [
      ".atomcat"
    ]
  },
  {
    "name": "application/atomsvc+xml",
    "fileTypes": [
      ".atomsvc"
    ]
  },
  {
    "name": "application/vnd.antix.game-component",
    "fileTypes": [
      ".atx"
    ]
  },
  {
    "name": "audio/basic",
    "fileTypes": [
      ".au",
      ".snd"
    ]
  },
  {
    "name": "video/x-msvideo",
    "fileTypes": [
      ".avi"
    ]
  },
  {
    "name": "application/applixware",
    "fileTypes": [
      ".aw"
    ]
  },
  {
    "name": "application/vnd.airzip.filesecure.azf",
    "fileTypes": [
      ".azf"
    ]
  },
  {
    "name": "application/vnd.airzip.filesecure.azs",
    "fileTypes": [
      ".azs"
    ]
  },
  {
    "name": "application/vnd.amazon.ebook",
    "fileTypes": [
      ".azw"
    ]
  },
  {
    "name": "application/x-msdownload",
    "fileTypes": [
      ".bat",
      ".com",
      ".dll",
      ".exe",
      ".msi"
    ]
  },
  {
    "name": "application/x-bcpio",
    "fileTypes": [
      ".bcpio"
    ]
  },
  {
    "name": "application/x-font-bdf",
    "fileTypes": [
      ".bdf"
    ]
  },
  {
    "name": "application/vnd.syncml.dm+wbxml",
    "fileTypes": [
      ".bdm"
    ]
  },
  {
    "name": "application/vnd.fujitsu.oasysprs",
    "fileTypes": [
      ".bh2"
    ]
  },
  {
    "name": "application/vnd.bmi",
    "fileTypes": [
      ".bmi"
    ]
  },
  {
    "name": "image/bmp",
    "fileTypes": [
      ".bmp"
    ]
  },
  {
    "name": "application/vnd.framemaker",
    "fileTypes": [
      ".book",
      ".fm",
      ".frame",
      ".maker"
    ]
  },
  {
    "name": "application/vnd.previewsystems.box",
    "fileTypes": [
      ".box"
    ]
  },
  {
    "name": "application/x-bzip2",
    "fileTypes": [
      ".boz",
      ".bz2"
    ]
  },
  {
    "name": "image/prs.btif",
    "fileTypes": [
      ".btif"
    ]
  },
  {
    "name": "application/x-bzip",
    "fileTypes": [
      ".bz"
    ]
  },
  {
    "name": "text/x-c",
    "fileTypes": [
      ".c",
      ".cc",
      ".cpp",
      ".cxx",
      ".dic",
      ".h",
      ".hh"
    ]
  },
  {
    "name": "application/vnd.clonk.c4group",
    "fileTypes": [
      ".c4d",
      ".c4f",
      ".c4g",
      ".c4p",
      ".c4u"
    ]
  },
  {
    "name": "application/vnd.ms-cab-compressed",
    "fileTypes": [
      ".cab"
    ]
  },
  {
    "name": "application/vnd.curl.car",
    "fileTypes": [
      ".car"
    ]
  },
  {
    "name": "application/vnd.ms-pki.seccat",
    "fileTypes": [
      ".cat"
    ]
  },
  {
    "name": "application/x-director",
    "fileTypes": [
      ".cct",
      ".cst",
      ".cxt",
      ".dcr",
      ".dir",
      ".dxr",
      ".fgd",
      ".swa",
      ".w3d"
    ]
  },
  {
    "name": "application/ccxml+xml",
    "fileTypes": [
      ".ccxml"
    ]
  },
  {
    "name": "application/vnd.contact.cmsg",
    "fileTypes": [
      ".cdbcmsg"
    ]
  },
  {
    "name": "application/x-netcdf",
    "fileTypes": [
      ".cdf",
      ".nc"
    ]
  },
  {
    "name": "application/vnd.mediastation.cdkey",
    "fileTypes": [
      ".cdkey"
    ]
  },
  {
    "name": "chemical/x-cdx",
    "fileTypes": [
      ".cdx"
    ]
  },
  {
    "name": "application/vnd.chemdraw+xml",
    "fileTypes": [
      ".cdxml"
    ]
  },
  {
    "name": "application/vnd.cinderella",
    "fileTypes": [
      ".cdy"
    ]
  },
  {
    "name": "application/pkix-cert",
    "fileTypes": [
      ".cer"
    ]
  },
  {
    "name": "image/cgm",
    "fileTypes": [
      ".cgm"
    ]
  },
  {
    "name": "application/x-chat",
    "fileTypes": [
      ".chat"
    ]
  },
  {
    "name": "application/vnd.ms-htmlhelp",
    "fileTypes": [
      ".chm"
    ]
  },
  {
    "name": "application/vnd.kde.kchart",
    "fileTypes": [
      ".chrt"
    ]
  },
  {
    "name": "chemical/x-cif",
    "fileTypes": [
      ".cif"
    ]
  },
  {
    "name": "application/vnd.anser-web-certificate-issue-initiation",
    "fileTypes": [
      ".cii"
    ]
  },
  {
    "name": "application/vnd.ms-artgalry",
    "fileTypes": [
      ".cil"
    ]
  },
  {
    "name": "application/vnd.claymore",
    "fileTypes": [
      ".cla"
    ]
  },
  {
    "name": "application/java-vm",
    "fileTypes": [
      ".class"
    ]
  },
  {
    "name": "application/vnd.crick.clicker.keyboard",
    "fileTypes": [
      ".clkk"
    ]
  },
  {
    "name": "application/vnd.crick.clicker.palette",
    "fileTypes": [
      ".clkp"
    ]
  },
  {
    "name": "application/vnd.crick.clicker.template",
    "fileTypes": [
      ".clkt"
    ]
  },
  {
    "name": "application/vnd.crick.clicker.wordbank",
    "fileTypes": [
      ".clkw"
    ]
  },
  {
    "name": "application/vnd.crick.clicker",
    "fileTypes": [
      ".clkx"
    ]
  },
  {
    "name": "application/x-msclip",
    "fileTypes": [
      ".clp"
    ]
  },
  {
    "name": "application/vnd.cosmocaller",
    "fileTypes": [
      ".cmc"
    ]
  },
  {
    "name": "chemical/x-cmdf",
    "fileTypes": [
      ".cmdf"
    ]
  },
  {
    "name": "chemical/x-cml",
    "fileTypes": [
      ".cml"
    ]
  },
  {
    "name": "application/vnd.yellowriver-custom-menu",
    "fileTypes": [
      ".cmp"
    ]
  },
  {
    "name": "image/x-cmx",
    "fileTypes": [
      ".cmx"
    ]
  },
  {
    "name": "application/vnd.rim.cod",
    "fileTypes": [
      ".cod"
    ]
  },
  {
    "name": "text/plain",
    "fileTypes": [
      ".conf",
      ".def",
      ".diff",
      ".in",
      ".ksh",
      ".list",
      ".log",
      ".pl",
      ".text",
      ".txt"
    ]
  },
  {
    "name": "application/vnd.debian.binary-package",
    "fileTypes": [
      ".deb",
      ".udeb"
    ]
  },
  {
    "name": "text/markdown",
    "fileTypes": [
      ".md",
      ".markdown",
      ".mdown",
      ".markdn"
    ]
  },
  {
    "name": "text/x-markdown",
    "deprecated": true,
    "useInstead": "text/markdown",
    "fileTypes": [
      ".md",
      ".markdown",
      ".mdown",
      ".markdn"
    ]
  },
  {
    "name": "application/wasm",
    "fileTypes": [
      ".wasm"
    ]
  },
  {
    "name": "application/x-cpio",
    "fileTypes": [
      ".cpio"
    ]
  },
  {
    "name": "application/mac-compactpro",
    "fileTypes": [
      ".cpt"
    ]
  },
  {
    "name": "application/x-mscardfile",
    "fileTypes": [
      ".crd"
    ]
  },
  {
    "name": "application/pkix-crl",
    "fileTypes": [
      ".crl"
    ]
  },
  {
    "name": "application/x-x509-ca-cert",
    "fileTypes": [
      ".crt",
      ".der"
    ]
  },
  {
    "name": "application/x-csh",
    "fileTypes": [
      ".csh"
    ]
  },
  {
    "name": "chemical/x-csml",
    "fileTypes": [
      ".csml"
    ]
  },
  {
    "name": "application/vnd.commonspace",
    "fileTypes": [
      ".csp"
    ]
  },
  {
    "name": "text/css",
    "fileTypes": [
      ".css"
    ]
  },
  {
    "name": "text/csv",
    "fileTypes": [
      ".csv"
    ]
  },
  {
    "name": "application/cu-seeme",
    "fileTypes": [
      ".cu"
    ]
  },
  {
    "name": "text/vnd.curl",
    "fileTypes": [
      ".curl"
    ]
  },
  {
    "name": "application/prs.cww",
    "fileTypes": [
      ".cww"
    ]
  },
  {
    "name": "application/vnd.mobius.daf",
    "fileTypes": [
      ".daf"
    ]
  },
  {
    "name": "application/vnd.fdsn.seed",
    "fileTypes": [
      ".dataless",
      ".seed"
    ]
  },
  {
    "name": "application/davmount+xml",
    "fileTypes": [
      ".davmount"
    ]
  },
  {
    "name": "text/vnd.curl.dcurl",
    "fileTypes": [
      ".dcurl"
    ]
  },
  {
    "name": "application/vnd.oma.dd2+xml",
    "fileTypes": [
      ".dd2"
    ]
  },
  {
    "name": "application/vnd.fujixerox.ddd",
    "fileTypes": [
      ".ddd"
    ]
  },
  {
    "name": "application/x-debian-package",
    "fileTypes": [
      ".deb",
      ".udeb"
    ]
  },
  {
    "name": "application/vnd.dreamfactory",
    "fileTypes": [
      ".dfac"
    ]
  },
  {
    "name": "application/vnd.mobius.dis",
    "fileTypes": [
      ".dis"
    ]
  },
  {
    "name": "image/vnd.djvu",
    "fileTypes": [
      ".djv",
      ".djvu"
    ]
  },
  {
    "name": "application/vnd.dna",
    "fileTypes": [
      ".dna"
    ]
  },
  {
    "name": "application/msword",
    "fileTypes": [
      ".doc",
      ".dot",
      ".wiz"
    ]
  },
  {
    "name": "application/vnd.ms-word.document.macroenabled.12",
    "fileTypes": [
      ".docm"
    ]
  },
  {
    "name": "application/vnd.openxmlformats-officedocument.wordprocessingml.document",
    "fileTypes": [
      ".docx"
    ]
  },
  {
    "name": "application/vnd.ms-word.template.macroenabled.12",
    "fileTypes": [
      ".dotm"
    ]
  },
  {
    "name": "application/vnd.openxmlformats-officedocument.wordprocessingml.template",
    "fileTypes": [
      ".dotx"
    ]
  },
  {
    "name": "application/vnd.osgi.dp",
    "fileTypes": [
      ".dp"
    ]
  },
  {
    "name": "application/vnd.dpgraph",
    "fileTypes": [
      ".dpg"
    ]
  },
  {
    "name": "text/prs.lines.tag",
    "fileTypes": [
      ".dsc"
    ]
  },
  {
    "name": "application/x-dtbook+xml",
    "fileTypes": [
      ".dtb"
    ]
  },
  {
    "name": "application/xml-dtd",
    "fileTypes": [
      ".dtd"
    ]
  },
  {
    "name": "audio/vnd.dts",
    "fileTypes": [
      ".dts"
    ]
  },
  {
    "name": "audio/vnd.dts.hd",
    "fileTypes": [
      ".dtshd"
    ]
  },
  {
    "name": "application/x-dvi",
    "fileTypes": [
      ".dvi"
    ]
  },
  {
    "name": "model/vnd.dwf",
    "fileTypes": [
      ".dwf"
    ]
  },
  {
    "name": "image/vnd.dwg",
    "fileTypes": [
      ".dwg"
    ]
  },
  {
    "name": "image/vnd.dxf",
    "fileTypes": [
      ".dxf"
    ]
  },
  {
    "name": "application/vnd.spotfire.dxp",
    "fileTypes": [
      ".dxp"
    ]
  },
  {
    "name": "audio/vnd.nuera.ecelp4800",
    "fileTypes": [
      ".ecelp4800"
    ]
  },
  {
    "name": "audio/vnd.nuera.ecelp7470",
    "fileTypes": [
      ".ecelp7470"
    ]
  },
  {
    "name": "audio/vnd.nuera.ecelp9600",
    "fileTypes": [
      ".ecelp9600"
    ]
  },
  {
    "name": "application/ecmascript",
    "fileTypes": [
      ".ecma"
    ]
  },
  {
    "name": "application/vnd.novadigm.edm",
    "fileTypes": [
      ".edm"
    ]
  },
  {
    "name": "application/vnd.novadigm.edx",
    "fileTypes": [
      ".edx"
    ]
  },
  {
    "name": "application/vnd.picsel",
    "fileTypes": [
      ".efif"
    ]
  },
  {
    "name": "application/vnd.pg.osasli",
    "fileTypes": [
      ".ei6"
    ]
  },
  {
    "name": "message/rfc822",
    "fileTypes": [
      ".eml",
      ".mht",
      ".mhtml",
      ".mime",
      ".nws"
    ]
  },
  {
    "name": "application/emma+xml",
    "fileTypes": [
      ".emma"
    ]
  },
  {
    "name": "audio/vnd.digital-winds",
    "fileTypes": [
      ".eol"
    ]
  },
  {
    "name": "application/vnd.ms-fontobject",
    "fileTypes": [
      ".eot"
    ]
  },
  {
    "name": "application/epub+zip",
    "fileTypes": [
      ".epub"
    ]
  },
  {
    "name": "application/vnd.eszigno3+xml",
    "fileTypes": [
      ".es3",
      ".et3"
    ]
  },
  {
    "name": "application/vnd.epson.esf",
    "fileTypes": [
      ".esf"
    ]
  },
  {
    "name": "text/x-setext",
    "fileTypes": [
      ".etx"
    ]
  },
  {
    "name": "application/vnd.novadigm.ext",
    "fileTypes": [
      ".ext"
    ]
  },
  {
    "name": "application/andrew-inset",
    "fileTypes": [
      ".ez"
    ]
  },
  {
    "name": "application/vnd.ezpix-album",
    "fileTypes": [
      ".ez2"
    ]
  },
  {
    "name": "application/vnd.ezpix-package",
    "fileTypes": [
      ".ez3"
    ]
  },
  {
    "name": "text/x-fortran",
    "fileTypes": [
      ".f",
      ".f77",
      ".f90",
      ".for"
    ]
  },
  {
    "name": "video/x-f4v",
    "fileTypes": [
      ".f4v"
    ]
  },
  {
    "name": "image/vnd.fastbidsheet",
    "fileTypes": [
      ".fbs"
    ]
  },
  {
    "name": "application/vnd.fdf",
    "fileTypes": [
      ".fdf"
    ]
  },
  {
    "name": "application/vnd.denovo.fcselayout-link",
    "fileTypes": [
      ".fe_launch"
    ]
  },
  {
    "name": "application/vnd.fujitsu.oasysgp",
    "fileTypes": [
      ".fg5"
    ]
  },
  {
    "name": "image/x-freehand",
    "fileTypes": [
      ".fh",
      ".fh4",
      ".fh5",
      ".fh7",
      ".fhc"
    ]
  },
  {
    "name": "application/x-xfig",
    "fileTypes": [
      ".fig"
    ]
  },
  {
    "name": "video/x-fli",
    "fileTypes": [
      ".fli"
    ]
  },
  {
    "name": "application/vnd.micrografx.flo",
    "fileTypes": [
      ".flo"
    ]
  },
  {
    "name": "video/x-flv",
    "fileTypes": [
      ".flv"
    ]
  },
  {
    "name": "application/vnd.kde.kivio",
    "fileTypes": [
      ".flw"
    ]
  },
  {
    "name": "text/vnd.fmi.flexstor",
    "fileTypes": [
      ".flx"
    ]
  },
  {
    "name": "text/vnd.fly",
    "fileTypes": [
      ".fly"
    ]
  },
  {
    "name": "application/vnd.frogans.fnc",
    "fileTypes": [
      ".fnc"
    ]
  },
  {
    "name": "image/vnd.fpx",
    "fileTypes": [
      ".fpx"
    ]
  },
  {
    "name": "application/vnd.fsc.weblaunch",
    "fileTypes": [
      ".fsc"
    ]
  },
  {
    "name": "image/vnd.fst",
    "fileTypes": [
      ".fst"
    ]
  },
  {
    "name": "application/vnd.fluxtime.clip",
    "fileTypes": [
      ".ftc"
    ]
  },
  {
    "name": "application/vnd.anser-web-funds-transfer-initiation",
    "fileTypes": [
      ".fti"
    ]
  },
  {
    "name": "video/vnd.fvt",
    "fileTypes": [
      ".fvt"
    ]
  },
  {
    "name": "application/vnd.fuzzysheet",
    "fileTypes": [
      ".fzs"
    ]
  },
  {
    "name": "image/g3fax",
    "fileTypes": [
      ".g3"
    ]
  },
  {
    "name": "application/vnd.groove-account",
    "fileTypes": [
      ".gac"
    ]
  },
  {
    "name": "model/vnd.gdl",
    "fileTypes": [
      ".gdl"
    ]
  },
  {
    "name": "application/vnd.dynageo",
    "fileTypes": [
      ".geo"
    ]
  },
  {
    "name": "application/vnd.geometry-explorer",
    "fileTypes": [
      ".gex",
      ".gre"
    ]
  },
  {
    "name": "application/vnd.geogebra.file",
    "fileTypes": [
      ".ggb"
    ]
  },
  {
    "name": "application/vnd.geogebra.tool",
    "fileTypes": [
      ".ggt"
    ]
  },
  {
    "name": "application/vnd.groove-help",
    "fileTypes": [
      ".ghf"
    ]
  },
  {
    "name": "image/gif",
    "fileTypes": [
      ".gif"
    ]
  },
  {
    "name": "application/vnd.groove-identity-message",
    "fileTypes": [
      ".gim"
    ]
  },
  {
    "name": "application/vnd.gmx",
    "fileTypes": [
      ".gmx"
    ]
  },
  {
    "name": "application/x-gnumeric",
    "fileTypes": [
      ".gnumeric"
    ]
  },
  {
    "name": "application/vnd.flographit",
    "fileTypes": [
      ".gph"
    ]
  },
  {
    "name": "application/vnd.grafeq",
    "fileTypes": [
      ".gqf",
      ".gqs"
    ]
  },
  {
    "name": "application/srgs",
    "fileTypes": [
      ".gram"
    ]
  },
  {
    "name": "application/vnd.groove-injector",
    "fileTypes": [
      ".grv"
    ]
  },
  {
    "name": "application/srgs+xml",
    "fileTypes": [
      ".grxml"
    ]
  },
  {
    "name": "application/x-font-ghostscript",
    "fileTypes": [
      ".gsf"
    ]
  },
  {
    "name": "application/x-gtar",
    "fileTypes": [
      ".gtar"
    ]
  },
  {
    "name": "application/vnd.groove-tool-message",
    "fileTypes": [
      ".gtm"
    ]
  },
  {
    "name": "model/vnd.gtw",
    "fileTypes": [
      ".gtw"
    ]
  },
  {
    "name": "text/vnd.graphviz",
    "fileTypes": [
      ".gv"
    ]
  },
  {
    "name": "application/x-gzip",
    "fileTypes": [
      ".gz",
      ".tgz"
    ]
  },
  {
    "name": "application/gzip",
    "fileTypes": [
      ".gz",
      ".tgz"
    ]
  },
  {
    "name": "video/h261",
    "fileTypes": [
      ".h261"
    ]
  },
  {
    "name": "gcode",
    "fileTypes": [
      ".gcode"
    ]
  },
  {
    "name": "video/h263",
    "fileTypes": [
      ".h263"
    ]
  },
  {
    "name": "video/h264",
    "fileTypes": [
      ".h264"
    ]
  },
  {
    "name": "application/vnd.hbci",
    "fileTypes": [
      ".hbci"
    ]
  },
  {
    "name": "application/vnd.gerber",
    "fileTypes": [
      ".gbr"
    ]
  },
  {
    "name": "application/x-hdf",
    "fileTypes": [
      ".hdf"
    ]
  },
  {
    "name": "application/winhlp",
    "fileTypes": [
      ".hlp"
    ]
  },
  {
    "name": "application/vnd.hp-hpgl",
    "fileTypes": [
      ".hpgl"
    ]
  },
  {
    "name": "application/vnd.hp-hpid",
    "fileTypes": [
      ".hpid"
    ]
  },
  {
    "name": "application/vnd.hp-hps",
    "fileTypes": [
      ".hps"
    ]
  },
  {
    "name": "application/mac-binhex40",
    "fileTypes": [
      ".hqx"
    ]
  },
  {
    "name": "application/vnd.kenameaapp",
    "fileTypes": [
      ".htke"
    ]
  },
  {
    "name": "text/html",
    "fileTypes": [
      ".htm",
      ".html"
    ]
  },
  {
    "name": "application/vnd.yamaha.hv-dic",
    "fileTypes": [
      ".hvd"
    ]
  },
  {
    "name": "application/vnd.yamaha.hv-voice",
    "fileTypes": [
      ".hvp"
    ]
  },
  {
    "name": "application/vnd.yamaha.hv-script",
    "fileTypes": [
      ".hvs"
    ]
  },
  {
    "name": "application/vnd.iccprofile",
    "fileTypes": [
      ".icc",
      ".icm"
    ]
  },
  {
    "name": "x-conference/x-cooltalk",
    "fileTypes": [
      ".ice"
    ]
  },
  {
    "name": "image/x-icon",
    "fileTypes": [
      ".ico"
    ]
  },
  {
    "name": "text/calendar",
    "fileTypes": [
      ".ics",
      ".ifb"
    ]
  },
  {
    "name": "image/ief",
    "fileTypes": [
      ".ief"
    ]
  },
  {
    "name": "application/vnd.shana.informed.formdata",
    "fileTypes": [
      ".ifm"
    ]
  },
  {
    "name": "model/iges",
    "fileTypes": [
      ".iges",
      ".igs"
    ]
  },
  {
    "name": "application/vnd.igloader",
    "fileTypes": [
      ".igl"
    ]
  },
  {
    "name": "application/vnd.micrografx.igx",
    "fileTypes": [
      ".igx"
    ]
  },
  {
    "name": "application/vnd.shana.informed.interchange",
    "fileTypes": [
      ".iif"
    ]
  },
  {
    "name": "application/vnd.accpac.simply.imp",
    "fileTypes": [
      ".imp"
    ]
  },
  {
    "name": "application/vnd.ms-ims",
    "fileTypes": [
      ".ims"
    ]
  },
  {
    "name": "application/vnd.shana.informed.package",
    "fileTypes": [
      ".ipk"
    ]
  },
  {
    "name": "application/vnd.ibm.rights-management",
    "fileTypes": [
      ".irm"
    ]
  },
  {
    "name": "application/vnd.irepository.package+xml",
    "fileTypes": [
      ".irp"
    ]
  },
  {
    "name": "application/vnd.shana.informed.formtemplate",
    "fileTypes": [
      ".itp"
    ]
  },
  {
    "name": "application/vnd.immervision-ivp",
    "fileTypes": [
      ".ivp"
    ]
  },
  {
    "name": "application/vnd.immervision-ivu",
    "fileTypes": [
      ".ivu"
    ]
  },
  {
    "name": "text/vnd.sun.j2me.app-descriptor",
    "fileTypes": [
      ".jad"
    ]
  },
  {
    "name": "application/vnd.jam",
    "fileTypes": [
      ".jam"
    ]
  },
  {
    "name": "application/java-archive",
    "fileTypes": [
      ".jar"
    ]
  },
  {
    "name": "text/x-java-source",
    "fileTypes": [
      ".java"
    ]
  },
  {
    "name": "application/vnd.jisp",
    "fileTypes": [
      ".jisp"
    ]
  },
  {
    "name": "application/vnd.hp-jlyt",
    "fileTypes": [
      ".jlt"
    ]
  },
  {
    "name": "application/x-java-jnlp-file",
    "fileTypes": [
      ".jnlp"
    ]
  },
  {
    "name": "application/vnd.joost.joda-archive",
    "fileTypes": [
      ".joda"
    ]
  },
  {
    "name": "image/jpeg",
    "fileTypes": [
      ".jpe",
      ".jpeg",
      ".jpg",
      ".pjpg",
      ".jfif",
      ".jfif-tbnl",
      ".jif"
    ]
  },
  {
    "name": "image/pjpeg",
    "fileTypes": [
      ".jpe",
      ".jpeg",
      ".jpg",
      ".pjpg",
      ".jfi",
      ".jfif",
      ".jfif-tbnl",
      ".jif"
    ]
  },
  {
    "name": "video/jpm",
    "fileTypes": [
      ".jpgm",
      ".jpm"
    ]
  },
  {
    "name": "video/jpeg",
    "fileTypes": [
      ".jpgv"
    ]
  },
  {
    "name": "application/x-trash",
    "fileTypes": []
  },
  {
    "name": "application/x-shellscript",
    "fileTypes": [
      ".sh"
    ]
  },
  {
    "name": "text/javascript",
    "fileTypes": [
      ".js"
    ]
  },
  {
    "name": "application/json",
    "fileTypes": [
      ".json"
    ]
  },
  {
    "name": "audio/midi",
    "fileTypes": [
      ".kar",
      ".mid",
      ".midi",
      ".rmi"
    ]
  },
  {
    "name": "audio/aiff",
    "fileTypes": [
      ".aiff",
      ".aif",
      ".aff"
    ]
  },
  {
    "name": "audio/opus",
    "fileTypes": [
      ".opus"
    ]
  },
  {
    "name": "application/vnd.kde.karbon",
    "fileTypes": [
      ".karbon"
    ]
  },
  {
    "name": "application/vnd.kde.kformula",
    "fileTypes": [
      ".kfo"
    ]
  },
  {
    "name": "application/vnd.kidspiration",
    "fileTypes": [
      ".kia"
    ]
  },
  {
    "name": "application/x-killustrator",
    "fileTypes": [
      ".kil"
    ]
  },
  {
    "name": "application/vnd.google-earth.kml+xml",
    "fileTypes": [
      ".kml"
    ]
  },
  {
    "name": "application/vnd.google-earth.kmz",
    "fileTypes": [
      ".kmz"
    ]
  },
  {
    "name": "application/vnd.kinar",
    "fileTypes": [
      ".kne",
      ".knp"
    ]
  },
  {
    "name": "application/vnd.kde.kontour",
    "fileTypes": [
      ".kon"
    ]
  },
  {
    "name": "application/vnd.kde.kpresenter",
    "fileTypes": [
      ".kpr",
      ".kpt"
    ]
  },
  {
    "name": "application/vnd.kde.kspread",
    "fileTypes": [
      ".ksp"
    ]
  },
  {
    "name": "application/vnd.kahootz",
    "fileTypes": [
      ".ktr",
      ".ktz"
    ]
  },
  {
    "name": "application/vnd.kde.kword",
    "fileTypes": [
      ".kwd",
      ".kwt"
    ]
  },
  {
    "name": "application/x-latex",
    "fileTypes": [
      ".latex"
    ]
  },
  {
    "name": "application/vnd.llamagraphics.life-balance.desktop",
    "fileTypes": [
      ".lbd"
    ]
  },
  {
    "name": "application/vnd.llamagraphics.life-balance.exchange+xml",
    "fileTypes": [
      ".lbe"
    ]
  },
  {
    "name": "application/vnd.hhe.lesson-player",
    "fileTypes": [
      ".les"
    ]
  },
  {
    "name": "application/vnd.route66.link66+xml",
    "fileTypes": [
      ".link66"
    ]
  },
  {
    "name": "application/lost+xml",
    "fileTypes": [
      ".lostxml"
    ]
  },
  {
    "name": "application/vnd.ms-lrm",
    "fileTypes": [
      ".lrm"
    ]
  },
  {
    "name": "application/vnd.frogans.ltf",
    "fileTypes": [
      ".ltf"
    ]
  },
  {
    "name": "audio/vnd.lucent.voice",
    "fileTypes": [
      ".lvp"
    ]
  },
  {
    "name": "application/vnd.lotus-wordpro",
    "fileTypes": [
      ".lwp"
    ]
  },
  {
    "name": "application/x-msmediaview",
    "fileTypes": [
      ".m13",
      ".m14",
      ".mvb"
    ]
  },
  {
    "name": "video/mpeg",
    "fileTypes": [
      ".m1v",
      ".m2v",
      ".mpa",
      ".mpe",
      ".mpeg",
      ".mpg"
    ]
  },
  {
    "name": "audio/mpeg",
    "fileTypes": [
      ".m2a",
      ".m3a",
      ".mp2",
      ".mp2a",
      ".mp3",
      ".mpga"
    ]
  },
  {
    "name": "audio/x-mpegurl",
    "fileTypes": [
      ".m3u"
    ]
  },
  {
    "name": "video/vnd.mpegurl",
    "fileTypes": [
      ".m4u",
      ".mxu"
    ]
  },
  {
    "name": "video/x-m4v",
    "fileTypes": [
      ".m4v"
    ]
  },
  {
    "name": "application/mathematica",
    "fileTypes": [
      ".ma",
      ".mb",
      ".nb"
    ]
  },
  {
    "name": "application/vnd.ecowin.chart",
    "fileTypes": [
      ".mag"
    ]
  },
  {
    "name": "text/troff",
    "fileTypes": [
      ".man",
      ".me",
      ".ms",
      ".roff",
      ".t",
      ".tr"
    ]
  },
  {
    "name": "application/mathml+xml",
    "fileTypes": [
      ".mathml",
      ".mml"
    ]
  },
  {
    "name": "text/mathml",
    "fileTypes": [
      ".mathml",
      ".mml"
    ]
  },
  {
    "name": "application/vnd.sqlite3",
    "fileTypes": [
      ".db",
      ".sqlite",
      ".sqlite3",
      ".db-wal",
      ".sqlite-wal",
      ".db-shm",
      ".sqlite-shm"
    ]
  },
  {
    "name": "application/x-sqlite3",
    "deprecated": true,
    "useInstead": "application/vnd.sqlite3",
    "fileTypes": [
      ".db",
      ".sqlite",
      ".sqlite3",
      ".db-wal",
      ".sqlite-wal",
      ".db-shm",
      ".sqlite-shm"
    ]
  },
  {
    "name": "application/vnd.mobius.mbk",
    "fileTypes": [
      ".mbk"
    ]
  },
  {
    "name": "application/mbox",
    "fileTypes": [
      ".mbox"
    ]
  },
  {
    "name": "application/vnd.medcalcdata",
    "fileTypes": [
      ".mc1"
    ]
  },
  {
    "name": "application/vnd.mcd",
    "fileTypes": [
      ".mcd"
    ]
  },
  {
    "name": "text/vnd.curl.mcurl",
    "fileTypes": [
      ".mcurl"
    ]
  },
  {
    "name": "application/x-msaccess",
    "fileTypes": [
      ".mdb"
    ]
  },
  {
    "name": "image/vnd.ms-modi",
    "fileTypes": [
      ".mdi"
    ]
  },
  {
    "name": "model/mesh",
    "fileTypes": [
      ".mesh",
      ".msh",
      ".silo"
    ]
  },
  {
    "name": "application/vnd.mfmp",
    "fileTypes": [
      ".mfm"
    ]
  },
  {
    "name": "application/vnd.proteus.magazine",
    "fileTypes": [
      ".mgz"
    ]
  },
  {
    "name": "application/vnd.mif",
    "fileTypes": [
      ".mif"
    ]
  },
  {
    "name": "video/mj2",
    "fileTypes": [
      ".mj2",
      ".mjp2"
    ]
  },
  {
    "name": "application/vnd.dolby.mlp",
    "fileTypes": [
      ".mlp"
    ]
  },
  {
    "name": "application/vnd.chipnuts.karaoke-mmd",
    "fileTypes": [
      ".mmd"
    ]
  },
  {
    "name": "application/vnd.smaf",
    "fileTypes": [
      ".mmf"
    ]
  },
  {
    "name": "image/vnd.fujixerox.edmics-mmr",
    "fileTypes": [
      ".mmr"
    ]
  },
  {
    "name": "application/x-msmoney",
    "fileTypes": [
      ".mny"
    ]
  },
  {
    "name": "application/x-mobipocket-ebook",
    "fileTypes": [
      ".mobi",
      ".prc"
    ]
  },
  {
    "name": "video/quicktime",
    "fileTypes": [
      ".mov",
      ".qt"
    ]
  },
  {
    "name": "video/x-sgi-movie",
    "fileTypes": [
      ".movie"
    ]
  },
  {
    "name": "video/mp4",
    "fileTypes": [
      ".mp4",
      ".mp4v",
      ".mpg4"
    ]
  },
  {
    "name": "application/x-iso9660-image",
    "fileTypes": [
      ".iso",
      ".isoimg",
      ".cdr"
    ]
  },
  {
    "name": "application/yaml",
    "fileTypes": [
      ".yaml",
      ".yml"
    ]
  },
  {
    "name": "application/mp4",
    "fileTypes": [
      ".mp4s"
    ]
  },
  {
    "name": "application/vnd.mophun.certificate",
    "fileTypes": [
      ".mpc"
    ]
  },
  {
    "name": "application/vnd.apple.installer+xml",
    "fileTypes": [
      ".mpkg"
    ]
  },
  {
    "name": "application/vnd.blueice.multipass",
    "fileTypes": [
      ".mpm"
    ]
  },
  {
    "name": "application/vnd.mophun.application",
    "fileTypes": [
      ".mpn"
    ]
  },
  {
    "name": "application/vnd.ms-project",
    "fileTypes": [
      ".mpp",
      ".mpt"
    ]
  },
  {
    "name": "application/vnd.ibm.minipay",
    "fileTypes": [
      ".mpy"
    ]
  },
  {
    "name": "application/vnd.mobius.mqy",
    "fileTypes": [
      ".mqy"
    ]
  },
  {
    "name": "application/marc",
    "fileTypes": [
      ".mrc"
    ]
  },
  {
    "name": "application/mediaservercontrol+xml",
    "fileTypes": [
      ".mscml"
    ]
  },
  {
    "name": "application/vnd.fdsn.mseed",
    "fileTypes": [
      ".mseed"
    ]
  },
  {
    "name": "application/vnd.mseq",
    "fileTypes": [
      ".mseq"
    ]
  },
  {
    "name": "application/vnd.epson.msf",
    "fileTypes": [
      ".msf"
    ]
  },
  {
    "name": "application/vnd.mobius.msl",
    "fileTypes": [
      ".msl"
    ]
  },
  {
    "name": "application/vnd.muvee.style",
    "fileTypes": [
      ".msty"
    ]
  },
  {
    "name": "model/vnd.mts",
    "fileTypes": [
      ".mts"
    ]
  },
  {
    "name": "application/vnd.musician",
    "fileTypes": [
      ".mus"
    ]
  },
  {
    "name": "application/vnd.recordare.musicxml+xml",
    "fileTypes": [
      ".musicxml"
    ]
  },
  {
    "name": "application/vnd.mfer",
    "fileTypes": [
      ".mwf"
    ]
  },
  {
    "name": "application/mxf",
    "fileTypes": [
      ".mxf"
    ]
  },
  {
    "name": "application/vnd.recordare.musicxml",
    "fileTypes": [
      ".mxl"
    ]
  },
  {
    "name": "application/xv+xml",
    "fileTypes": [
      ".mxml",
      ".xhvml",
      ".xvm",
      ".xvml"
    ]
  },
  {
    "name": "application/vnd.triscape.mxs",
    "fileTypes": [
      ".mxs"
    ]
  },
  {
    "name": "application/vnd.nokia.n-gage.symbian.install",
    "fileTypes": [
      ".n-gage"
    ]
  },
  {
    "name": "application/x-dtbncx+xml",
    "fileTypes": [
      ".ncx"
    ]
  },
  {
    "name": "application/vnd.nokia.n-gage.data",
    "fileTypes": [
      ".ngdat"
    ]
  },
  {
    "name": "application/vnd.neurolanguage.nlu",
    "fileTypes": [
      ".nlu"
    ]
  },
  {
    "name": "application/vnd.enliven",
    "fileTypes": [
      ".nml"
    ]
  },
  {
    "name": "application/vnd.noblenet-directory",
    "fileTypes": [
      ".nnd"
    ]
  },
  {
    "name": "application/vnd.noblenet-sealer",
    "fileTypes": [
      ".nns"
    ]
  },
  {
    "name": "application/vnd.noblenet-web",
    "fileTypes": [
      ".nnw"
    ]
  },
  {
    "name": "image/vnd.net-fpx",
    "fileTypes": [
      ".npx"
    ]
  },
  {
    "name": "application/vnd.lotus-notes",
    "fileTypes": [
      ".nsf"
    ]
  },
  {
    "name": "application/vnd.fujitsu.oasys2",
    "fileTypes": [
      ".oa2"
    ]
  },
  {
    "name": "application/vnd.fujitsu.oasys3",
    "fileTypes": [
      ".oa3"
    ]
  },
  {
    "name": "application/vnd.fujitsu.oasys",
    "fileTypes": [
      ".oas"
    ]
  },
  {
    "name": "application/x-msbinder",
    "fileTypes": [
      ".obd"
    ]
  },
  {
    "name": "application/oda",
    "fileTypes": [
      ".oda"
    ]
  },
  {
    "name": "application/vnd.oasis.opendocument.database",
    "fileTypes": [
      ".odb"
    ]
  },
  {
    "name": "application/vnd.oasis.opendocument.chart",
    "fileTypes": [
      ".odc"
    ]
  },
  {
    "name": "application/vnd.oasis.opendocument.formula",
    "fileTypes": [
      ".odf"
    ]
  },
  {
    "name": "application/vnd.oasis.opendocument.formula-template",
    "fileTypes": [
      ".odft"
    ]
  },
  {
    "name": "application/vnd.oasis.opendocument.graphics",
    "fileTypes": [
      ".odg"
    ]
  },
  {
    "name": "application/vnd.oasis.opendocument.image",
    "fileTypes": [
      ".odi"
    ]
  },
  {
    "name": "application/vnd.oasis.opendocument.presentation",
    "fileTypes": [
      ".odp"
    ]
  },
  {
    "name": "application/vnd.oasis.opendocument.spreadsheet",
    "fileTypes": [
      ".ods"
    ]
  },
  {
    "name": "application/vnd.oasis.opendocument.text",
    "fileTypes": [
      ".odt"
    ]
  },
  {
    "name": "audio/ogg",
    "fileTypes": [
      ".oga",
      ".ogg",
      ".spx"
    ]
  },
  {
    "name": "video/x-matroska",
    "fileTypes": [
      ".mkv"
    ]
  },
  {
    "name": "audio/x-matroska",
    "fileTypes": [
      ".mka"
    ]
  },
  {
    "name": "video/ogg",
    "fileTypes": [
      ".ogv"
    ]
  },
  {
    "name": "application/ogg",
    "fileTypes": [
      ".ogx"
    ]
  },
  {
    "name": "application/onenote",
    "fileTypes": [
      ".onepkg",
      ".onetmp",
      ".onetoc",
      ".onetoc2"
    ]
  },
  {
    "name": "application/oebps-package+xml",
    "fileTypes": [
      ".opf"
    ]
  },
  {
    "name": "application/vnd.palm",
    "fileTypes": [
      ".oprc",
      ".pdb",
      ".pqa"
    ]
  },
  {
    "name": "application/vnd.lotus-organizer",
    "fileTypes": [
      ".org"
    ]
  },
  {
    "name": "application/vnd.yamaha.openscoreformat",
    "fileTypes": [
      ".osf"
    ]
  },
  {
    "name": "application/vnd.yamaha.openscoreformat.osfpvg+xml",
    "fileTypes": [
      ".osfpvg"
    ]
  },
  {
    "name": "application/vnd.oasis.opendocument.chart-template",
    "fileTypes": [
      ".otc"
    ]
  },
  {
    "name": "font/woff",
    "fileTypes": [
      ".woff"
    ]
  },
  {
    "name": "font/woff2",
    "fileTypes": [
      ".woff2"
    ]
  },
  {
    "name": "application/x-redhat-package-manager",
    "fileTypes": [
      ".rpa"
    ]
  },
  {
    "name": "application/x-perl",
    "fileTypes": [
      ".pm",
      ".pl"
    ]
  },
  {
    "name": "audio/webm",
    "fileTypes": [
      ".weba"
    ]
  },
  {
    "name": "video/webm",
    "fileTypes": [
      ".webm"
    ]
  },
  {
    "name": "image/webp",
    "fileTypes": [
      ".webp"
    ]
  },
  {
    "name": "application/x-font-otf",
    "fileTypes": [
      ".otf"
    ]
  },
  {
    "name": "font/otf",
    "fileTypes": [
      ".otf"
    ]
  },
  {
    "name": "application/vnd.oasis.opendocument.graphics-template",
    "fileTypes": [
      ".otg"
    ]
  },
  {
    "name": "application/vnd.oasis.opendocument.text-web",
    "fileTypes": [
      ".oth"
    ]
  },
  {
    "name": "application/vnd.oasis.opendocument.image-template",
    "fileTypes": [
      ".oti"
    ]
  },
  {
    "name": "application/vnd.oasis.opendocument.text-master",
    "fileTypes": [
      ".otm"
    ]
  },
  {
    "name": "application/vnd.oasis.opendocument.presentation-template",
    "fileTypes": [
      ".otp"
    ]
  },
  {
    "name": "application/vnd.oasis.opendocument.spreadsheet-template",
    "fileTypes": [
      ".ots"
    ]
  },
  {
    "name": "application/vnd.oasis.opendocument.text-template",
    "fileTypes": [
      ".ott"
    ]
  },
  {
    "name": "application/vnd.openofficeorg.extension",
    "fileTypes": [
      ".oxt"
    ]
  },
  {
    "name": "text/x-pascal",
    "fileTypes": [
      ".p",
      ".pas",
      ".pp",
      ".inc"
    ]
  },
  {
    "name": "application/pkcs10",
    "fileTypes": [
      ".p10"
    ]
  },
  {
    "name": "application/x-pkcs12",
    "fileTypes": [
      ".p12",
      ".pfx"
    ]
  },
  {
    "name": "application/x-pkcs7-certificates",
    "fileTypes": [
      ".p7b",
      ".spc"
    ]
  },
  {
    "name": "application/pkcs7-mime",
    "fileTypes": [
      ".p7c",
      ".p7m"
    ]
  },
  {
    "name": "application/x-pkcs7-certreqresp",
    "deprecated": true,
    "useInstead": "application/pkcs7-mime",
    "fileTypes": [
      ".p7r"
    ]
  },
  {
    "name": "application/pkcs7-signature",
    "fileTypes": [
      ".p7s"
    ]
  },
  {
    "name": "application/vnd.powerbuilder6",
    "fileTypes": [
      ".pbd"
    ]
  },
  {
    "name": "image/x-portable-bitmap",
    "fileTypes": [
      ".pbm"
    ]
  },
  {
    "name": "application/x-font-pcf",
    "fileTypes": [
      ".pcf"
    ]
  },
  {
    "name": "application/vnd.hp-pcl",
    "fileTypes": [
      ".pcl"
    ]
  },
  {
    "name": "application/vnd.hp-pclxl",
    "fileTypes": [
      ".pclxl"
    ]
  },
  {
    "name": "image/x-pict",
    "fileTypes": [
      ".pct",
      ".pic"
    ]
  },
  {
    "name": "application/vnd.curl.pcurl",
    "fileTypes": [
      ".pcurl"
    ]
  },
  {
    "name": "image/x-pcx",
    "fileTypes": [
      ".pcx"
    ]
  },
  {
    "name": "application/pdf",
    "fileTypes": [
      ".pdf"
    ]
  },
  {
    "name": "application/font-tdpfr",
    "fileTypes": [
      ".pfr"
    ]
  },
  {
    "name": "image/x-portable-graymap",
    "fileTypes": [
      ".pgm"
    ]
  },
  {
    "name": "application/x-chess-pgn",
    "fileTypes": [
      ".pgn"
    ]
  },
  {
    "name": "application/pgp-encrypted",
    "fileTypes": [
      ".pgp"
    ]
  },
  {
    "name": "application/pkixcmp",
    "fileTypes": [
      ".pki"
    ]
  },
  {
    "name": "application/pkix-pkipath",
    "fileTypes": [
      ".pkipath"
    ]
  },
  {
    "name": "application/vnd.3gpp.pic-bw-large",
    "fileTypes": [
      ".plb"
    ]
  },
  {
    "name": "application/vnd.mobius.plc",
    "fileTypes": [
      ".plc"
    ]
  },
  {
    "name": "application/vnd.pocketlearn",
    "fileTypes": [
      ".plf"
    ]
  },
  {
    "name": "application/pls+xml",
    "fileTypes": [
      ".pls"
    ]
  },
  {
    "name": "application/vnd.ctc-posml",
    "fileTypes": [
      ".pml"
    ]
  },
  {
    "name": "image/png",
    "fileTypes": [
      ".png"
    ]
  },
  {
    "name": "image/x-portable-anymap",
    "fileTypes": [
      ".pnm"
    ]
  },
  {
    "name": "application/vnd.macports.portpkg",
    "fileTypes": [
      ".portpkg"
    ]
  },
  {
    "name": "application/vnd.ms-powerpoint",
    "fileTypes": [
      ".pot",
      ".ppa",
      ".pps",
      ".ppt",
      ".pwz"
    ]
  },
  {
    "name": "application/vnd.ms-powerpoint.template.macroenabled.12",
    "fileTypes": [
      ".potm"
    ]
  },
  {
    "name": "application/vnd.openxmlformats-officedocument.presentationml.template",
    "fileTypes": [
      ".potx"
    ]
  },
  {
    "name": "application/vnd.ms-powerpoint.addin.macroenabled.12",
    "fileTypes": [
      ".ppam"
    ]
  },
  {
    "name": "application/vnd.cups-ppd",
    "fileTypes": [
      ".ppd"
    ]
  },
  {
    "name": "image/x-portable-pixmap",
    "fileTypes": [
      ".ppm"
    ]
  },
  {
    "name": "application/vnd.ms-powerpoint.slideshow.macroenabled.12",
    "fileTypes": [
      ".ppsm"
    ]
  },
  {
    "name": "application/vnd.openxmlformats-officedocument.presentationml.slideshow",
    "fileTypes": [
      ".ppsx"
    ]
  },
  {
    "name": "application/vnd.ms-powerpoint.presentation.macroenabled.12",
    "fileTypes": [
      ".pptm"
    ]
  },
  {
    "name": "application/vnd.openxmlformats-officedocument.presentationml.presentation",
    "fileTypes": [
      ".pptx"
    ]
  },
  {
    "name": "application/vnd.lotus-freelance",
    "fileTypes": [
      ".pre"
    ]
  },
  {
    "name": "application/pics-rules",
    "fileTypes": [
      ".prf"
    ]
  },
  {
    "name": "application/prql",
    "fileTypes": [
      ".prql"
    ]
  },
  {
    "name": "application/vnd.3gpp.pic-bw-small",
    "fileTypes": [
      ".psb"
    ]
  },
  {
    "name": "image/vnd.adobe.photoshop",
    "fileTypes": [
      ".psd"
    ]
  },
  {
    "name": "application/x-font-linux-psf",
    "fileTypes": [
      ".psf"
    ]
  },
  {
    "name": "application/vnd.pvi.ptid1",
    "fileTypes": [
      ".ptid"
    ]
  },
  {
    "name": "application/x-mspublisher",
    "fileTypes": [
      ".pub"
    ]
  },
  {
    "name": "application/vnd.3gpp.pic-bw-var",
    "fileTypes": [
      ".pvb"
    ]
  },
  {
    "name": "application/vnd.3m.post-it-notes",
    "fileTypes": [
      ".pwn"
    ]
  },
  {
    "name": "text/x-python",
    "fileTypes": [
      ".py"
    ]
  },
  {
    "name": "audio/vnd.ms-playready.media.pya",
    "fileTypes": [
      ".pya"
    ]
  },
  {
    "name": "application/x-python-code",
    "fileTypes": [
      ".pyc",
      ".pyo"
    ]
  },
  {
    "name": "video/vnd.ms-playready.media.pyv",
    "fileTypes": [
      ".pyv"
    ]
  },
  {
    "name": "application/vnd.epson.quickanime",
    "fileTypes": [
      ".qam"
    ]
  },
  {
    "name": "application/vnd.intu.qbo",
    "fileTypes": [
      ".qbo"
    ]
  },
  {
    "name": "application/vnd.intu.qfx",
    "fileTypes": [
      ".qfx"
    ]
  },
  {
    "name": "application/vnd.publishare-delta-tree",
    "fileTypes": [
      ".qps"
    ]
  },
  {
    "name": "application/vnd.quark.quarkxpress",
    "fileTypes": [
      ".qwd",
      ".qwt",
      ".qxb",
      ".qxd",
      ".qxl",
      ".qxt"
    ]
  },
  {
    "name": "audio/x-pn-realaudio",
    "fileTypes": [
      ".ra",
      ".ram"
    ]
  },
  {
    "name": "application/vnd.rar",
    "fileTypes": [
      ".rar"
    ]
  },
  {
    "name": "application/x-rar-compressed",
    "deprecated": true,
    "useInstead": "application/vnd.rar",
    "fileTypes": [
      ".rar"
    ]
  },
  {
    "name": "image/x-cmu-raster",
    "fileTypes": [
      ".ras"
    ]
  },
  {
    "name": "application/vnd.ipunplugged.rcprofile",
    "fileTypes": [
      ".rcprofile"
    ]
  },
  {
    "name": "application/rdf+xml",
    "fileTypes": [
      ".rdf"
    ]
  },
  {
    "name": "application/vnd.data-vision.rdz",
    "fileTypes": [
      ".rdz"
    ]
  },
  {
    "name": "application/vnd.businessobjects",
    "fileTypes": [
      ".rep"
    ]
  },
  {
    "name": "application/x-dtbresource+xml",
    "fileTypes": [
      ".res"
    ]
  },
  {
    "name": "image/x-rgb",
    "fileTypes": [
      ".rgb"
    ]
  },
  {
    "name": "application/reginfo+xml",
    "fileTypes": [
      ".rif"
    ]
  },
  {
    "name": "application/resource-lists+xml",
    "fileTypes": [
      ".rl"
    ]
  },
  {
    "name": "image/vnd.fujixerox.edmics-rlc",
    "fileTypes": [
      ".rlc"
    ]
  },
  {
    "name": "application/resource-lists-diff+xml",
    "fileTypes": [
      ".rld"
    ]
  },
  {
    "name": "application/vnd.rn-realmedia",
    "fileTypes": [
      ".rm"
    ]
  },
  {
    "name": "audio/x-pn-realaudio-plugin",
    "fileTypes": [
      ".rmp"
    ]
  },
  {
    "name": "application/vnd.jcp.javame.midlet-rms",
    "fileTypes": [
      ".rms"
    ]
  },
  {
    "name": "application/relax-ng-compact-syntax",
    "fileTypes": [
      ".rnc"
    ]
  },
  {
    "name": "application/x-rpm",
    "fileTypes": [
      ".rpm"
    ]
  },
  {
    "name": "application/vnd.nokia.radio-presets",
    "fileTypes": [
      ".rpss"
    ]
  },
  {
    "name": "application/vnd.nokia.radio-preset",
    "fileTypes": [
      ".rpst"
    ]
  },
  {
    "name": "application/sparql-query",
    "fileTypes": [
      ".rq"
    ]
  },
  {
    "name": "application/rls-services+xml",
    "fileTypes": [
      ".rs"
    ]
  },
  {
    "name": "application/rsd+xml",
    "fileTypes": [
      ".rsd"
    ]
  },
  {
    "name": "application/rss+xml",
    "fileTypes": [
      ".rss",
      ".xml"
    ]
  },
  {
    "name": "application/rtf",
    "fileTypes": [
      ".rtf"
    ]
  },
  {
    "name": "text/richtext",
    "fileTypes": [
      ".rtx"
    ]
  },
  {
    "name": "application/vnd.yamaha.smaf-audio",
    "fileTypes": [
      ".saf"
    ]
  },
  {
    "name": "application/sbml+xml",
    "fileTypes": [
      ".sbml"
    ]
  },
  {
    "name": "application/vnd.ibm.secure-container",
    "fileTypes": [
      ".sc"
    ]
  },
  {
    "name": "application/x-msschedule",
    "fileTypes": [
      ".scd"
    ]
  },
  {
    "name": "application/vnd.lotus-screencam",
    "fileTypes": [
      ".scm"
    ]
  },
  {
    "name": "application/scvp-cv-request",
    "fileTypes": [
      ".scq"
    ]
  },
  {
    "name": "application/scvp-cv-response",
    "fileTypes": [
      ".scs"
    ]
  },
  {
    "name": "text/vnd.curl.scurl",
    "fileTypes": [
      ".scurl"
    ]
  },
  {
    "name": "application/vnd.stardivision.draw",
    "fileTypes": [
      ".sda"
    ]
  },
  {
    "name": "application/vnd.stardivision.calc",
    "fileTypes": [
      ".sdc"
    ]
  },
  {
    "name": "application/vnd.stardivision.impress",
    "fileTypes": [
      ".sdd"
    ]
  },
  {
    "name": "application/vnd.solent.sdkm+xml",
    "fileTypes": [
      ".sdkd",
      ".sdkm"
    ]
  },
  {
    "name": "application/sdp",
    "fileTypes": [
      ".sdp"
    ]
  },
  {
    "name": "application/vnd.stardivision.writer",
    "fileTypes": [
      ".sdw",
      ".vor"
    ]
  },
  {
    "name": "application/vnd.seemail",
    "fileTypes": [
      ".see"
    ]
  },
  {
    "name": "application/vnd.sema",
    "fileTypes": [
      ".sema"
    ]
  },
  {
    "name": "application/vnd.semd",
    "fileTypes": [
      ".semd"
    ]
  },
  {
    "name": "application/vnd.semf",
    "fileTypes": [
      ".semf"
    ]
  },
  {
    "name": "application/java-serialized-object",
    "fileTypes": [
      ".ser"
    ]
  },
  {
    "name": "application/set-payment-initiation",
    "fileTypes": [
      ".setpay"
    ]
  },
  {
    "name": "application/set-registration-initiation",
    "fileTypes": [
      ".setreg"
    ]
  },
  {
    "name": "application/vnd.hydrostatix.sof-data",
    "fileTypes": [
      ".sfd-hdstx"
    ]
  },
  {
    "name": "application/vnd.spotfire.sfs",
    "fileTypes": [
      ".sfs"
    ]
  },
  {
    "name": "application/vnd.stardivision.writer-global",
    "fileTypes": [
      ".sgl"
    ]
  },
  {
    "name": "text/sgml",
    "fileTypes": [
      ".sgm",
      ".sgml"
    ]
  },
  {
    "name": "application/x-sh",
    "fileTypes": [
      ".sh"
    ]
  },
  {
    "name": "application/x-shar",
    "fileTypes": [
      ".shar"
    ]
  },
  {
    "name": "application/shf+xml",
    "fileTypes": [
      ".shf"
    ]
  },
  {
    "name": "text/vnd.wap.si",
    "fileTypes": [
      ".si"
    ]
  },
  {
    "name": "application/vnd.wap.sic",
    "fileTypes": [
      ".sic"
    ]
  },
  {
    "name": "application/vnd.symbian.install",
    "fileTypes": [
      ".sis",
      ".sisx"
    ]
  },
  {
    "name": "application/x-stuffit",
    "fileTypes": [
      ".sit"
    ]
  },
  {
    "name": "application/x-stuffitx",
    "fileTypes": [
      ".sitx"
    ]
  },
  {
    "name": "application/vnd.koan",
    "fileTypes": [
      ".skd",
      ".skm",
      ".skp",
      ".skt"
    ]
  },
  {
    "name": "text/vnd.wap.sl",
    "fileTypes": [
      ".sl"
    ]
  },
  {
    "name": "application/vnd.wap.slc",
    "fileTypes": [
      ".slc"
    ]
  },
  {
    "name": "application/vnd.ms-powerpoint.slide.macroenabled.12",
    "fileTypes": [
      ".sldm"
    ]
  },
  {
    "name": "application/vnd.openxmlformats-officedocument.presentationml.slide",
    "fileTypes": [
      ".sldx"
    ]
  },
  {
    "name": "application/vnd.epson.salt",
    "fileTypes": [
      ".slt"
    ]
  },
  {
    "name": "application/vnd.stardivision.math",
    "fileTypes": [
      ".smf"
    ]
  },
  {
    "name": "application/smil+xml",
    "fileTypes": [
      ".smi",
      ".smil"
    ]
  },
  {
    "name": "application/x-font-snf",
    "fileTypes": [
      ".snf"
    ]
  },
  {
    "name": "application/vnd.yamaha.smaf-phrase",
    "fileTypes": [
      ".spf"
    ]
  },
  {
    "name": "application/x-futuresplash",
    "fileTypes": [
      ".spl"
    ]
  },
  {
    "name": "text/vnd.in3d.spot",
    "fileTypes": [
      ".spot"
    ]
  },
  {
    "name": "application/scvp-vp-response",
    "fileTypes": [
      ".spp"
    ]
  },
  {
    "name": "application/scvp-vp-request",
    "fileTypes": [
      ".spq"
    ]
  },
  {
    "name": "application/x-wais-source",
    "fileTypes": [
      ".src"
    ]
  },
  {
    "name": "application/sparql-results+xml",
    "fileTypes": [
      ".srx"
    ]
  },
  {
    "name": "application/vnd.kodak-descriptor",
    "fileTypes": [
      ".sse"
    ]
  },
  {
    "name": "application/vnd.epson.ssf",
    "fileTypes": [
      ".ssf"
    ]
  },
  {
    "name": "application/ssml+xml",
    "fileTypes": [
      ".ssml"
    ]
  },
  {
    "name": "application/vnd.sun.xml.calc.template",
    "fileTypes": [
      ".stc"
    ]
  },
  {
    "name": "application/vnd.sun.xml.draw.template",
    "fileTypes": [
      ".std"
    ]
  },
  {
    "name": "application/vnd.wt.stf",
    "fileTypes": [
      ".stf"
    ]
  },
  {
    "name": "application/vnd.sun.xml.impress.template",
    "fileTypes": [
      ".sti"
    ]
  },
  {
    "name": "application/hyperstudio",
    "fileTypes": [
      ".stk"
    ]
  },
  {
    "name": "application/vnd.ms-pki.stl",
    "fileTypes": [
      ".stl"
    ]
  },
  {
    "name": "application/vnd.pg.format",
    "fileTypes": [
      ".str"
    ]
  },
  {
    "name": "application/vnd.sun.xml.writer.template",
    "fileTypes": [
      ".stw"
    ]
  },
  {
    "name": "application/vnd.sus-calendar",
    "fileTypes": [
      ".sus",
      ".susp"
    ]
  },
  {
    "name": "application/x-sv4cpio",
    "fileTypes": [
      ".sv4cpio"
    ]
  },
  {
    "name": "application/x-sv4crc",
    "fileTypes": [
      ".sv4crc"
    ]
  },
  {
    "name": "application/vnd.svd",
    "fileTypes": [
      ".svd"
    ]
  },
  {
    "name": "image/svg+xml",
    "fileTypes": [
      ".svg",
      ".svgz"
    ]
  },
  {
    "name": "application/x-shockwave-flash",
    "fileTypes": [
      ".swf"
    ]
  },
  {
    "name": "application/vnd.arastra.swi",
    "fileTypes": [
      ".swi"
    ]
  },
  {
    "name": "application/vnd.sun.xml.calc",
    "fileTypes": [
      ".sxc"
    ]
  },
  {
    "name": "application/vnd.sun.xml.draw",
    "fileTypes": [
      ".sxd"
    ]
  },
  {
    "name": "application/vnd.sun.xml.writer.global",
    "fileTypes": [
      ".sxg"
    ]
  },
  {
    "name": "application/vnd.sun.xml.impress",
    "fileTypes": [
      ".sxi"
    ]
  },
  {
    "name": "application/vnd.sun.xml.math",
    "fileTypes": [
      ".sxm"
    ]
  },
  {
    "name": "application/vnd.sun.xml.writer",
    "fileTypes": [
      ".sxw"
    ]
  },
  {
    "name": "application/vnd.tao.intent-module-archive",
    "fileTypes": [
      ".tao"
    ]
  },
  {
    "name": "application/x-tar",
    "fileTypes": [
      ".tar"
    ]
  },
  {
    "name": "application/vnd.3gpp2.tcap",
    "fileTypes": [
      ".tcap"
    ]
  },
  {
    "name": "application/x-tcl",
    "fileTypes": [
      ".tcl"
    ]
  },
  {
    "name": "application/vnd.smart.teacher",
    "fileTypes": [
      ".teacher"
    ]
  },
  {
    "name": "application/x-tex",
    "fileTypes": [
      ".tex"
    ]
  },
  {
    "name": "application/x-texinfo",
    "fileTypes": [
      ".texi",
      ".texinfo"
    ]
  },
  {
    "name": "application/x-tex-tfm",
    "fileTypes": [
      ".tfm"
    ]
  },
  {
    "name": "image/tiff",
    "fileTypes": [
      ".tif",
      ".tiff"
    ]
  },
  {
    "name": "application/vnd.tmobile-livetv",
    "fileTypes": [
      ".tmo"
    ]
  },
  {
    "name": "application/x-bittorrent",
    "fileTypes": [
      ".torrent"
    ]
  },
  {
    "name": "application/vnd.groove-tool-template",
    "fileTypes": [
      ".tpl"
    ]
  },
  {
    "name": "application/vnd.trid.tpt",
    "fileTypes": [
      ".tpt"
    ]
  },
  {
    "name": "application/vnd.trueapp",
    "fileTypes": [
      ".tra"
    ]
  },
  {
    "name": "application/x-msterminal",
    "fileTypes": [
      ".trm"
    ]
  },
  {
    "name": "text/tab-separated-values",
    "fileTypes": [
      ".tsv"
    ]
  },
  {
    "name": "application/x-font-ttf",
    "fileTypes": [
      ".ttc",
      ".ttf"
    ]
  },
  {
    "name": "application/vnd.simtech-mindmapper",
    "fileTypes": [
      ".twd",
      ".twds"
    ]
  },
  {
    "name": "application/vnd.genomatix.tuxedo",
    "fileTypes": [
      ".txd"
    ]
  },
  {
    "name": "application/vnd.mobius.txf",
    "fileTypes": [
      ".txf"
    ]
  },
  {
    "name": "application/vnd.ufdl",
    "fileTypes": [
      ".ufd",
      ".ufdl"
    ]
  },
  {
    "name": "test/mimetype",
    "fileTypes": [
      ".test"
    ]
  },
  {
    "name": "application/vnd.umajin",
    "fileTypes": [
      ".umj"
    ]
  },
  {
    "name": "application/vnd.unity",
    "fileTypes": [
      ".unityweb"
    ]
  },
  {
    "name": "application/vnd.uoml+xml",
    "fileTypes": [
      ".uoml"
    ]
  },
  {
    "name": "text/uri-list",
    "fileTypes": [
      ".uri",
      ".uris",
      ".urls"
    ]
  },
  {
    "name": "application/x-ustar",
    "fileTypes": [
      ".ustar"
    ]
  },
  {
    "name": "application/vnd.uiq.theme",
    "fileTypes": [
      ".utz"
    ]
  },
  {
    "name": "text/x-uuencode",
    "fileTypes": [
      ".uu"
    ]
  },
  {
    "name": "application/x-cdlink",
    "fileTypes": [
      ".vcd"
    ]
  },
  {
    "name": "text/x-vcard",
    "fileTypes": [
      ".vcf"
    ]
  },
  {
    "name": "application/vnd.groove-vcard",
    "fileTypes": [
      ".vcg"
    ]
  },
  {
    "name": "text/x-vcalendar",
    "fileTypes": [
      ".vcs"
    ]
  },
  {
    "name": "application/vnd.vcx",
    "fileTypes": [
      ".vcx"
    ]
  },
  {
    "name": "application/vnd.visionary",
    "fileTypes": [
      ".vis"
    ]
  },
  {
    "name": "video/vnd.vivo",
    "fileTypes": [
      ".viv"
    ]
  },
  {
    "name": "model/vrml",
    "fileTypes": [
      ".vrml",
      ".wrl"
    ]
  },
  {
    "name": "application/vnd.visio",
    "fileTypes": [
      ".vsd",
      ".vss",
      ".vst",
      ".vsw",
      ".vsdx",
      ".vssx",
      ".vstx",
      ".vssm",
      ".vstm"
    ]
  },
  {
    "name": "application/vnd.vsf",
    "fileTypes": [
      ".vsf"
    ]
  },
  {
    "name": "model/vnd.vtu",
    "fileTypes": [
      ".vtu"
    ]
  },
  {
    "name": "application/voicexml+xml",
    "fileTypes": [
      ".vxml"
    ]
  },
  {
    "name": "application/x-doom",
    "fileTypes": [
      ".wad"
    ]
  },
  {
    "name": "video/mp2t",
    "fileTypes": [
      ".ts"
    ]
  },
  {
    "name": "audio/vnd.wav",
    "fileTypes": [
      ".wav"
    ]
  },
  {
    "name": "audio/x-ms-wax",
    "fileTypes": [
      ".wax"
    ]
  },
  {
    "name": "image/vnd.wap.wbmp",
    "fileTypes": [
      ".wbmp"
    ]
  },
  {
    "name": "application/vnd.criticaltools.wbs+xml",
    "fileTypes": [
      ".wbs"
    ]
  },
  {
    "name": "application/vnd.wap.wbxml",
    "fileTypes": [
      ".wbxml"
    ]
  },
  {
    "name": "application/vnd.ms-works",
    "fileTypes": [
      ".wcm",
      ".wdb",
      ".wks",
      ".wps"
    ]
  },
  {
    "name": "video/x-ms-wm",
    "fileTypes": [
      ".wm"
    ]
  },
  {
    "name": "audio/x-ms-wma",
    "fileTypes": [
      ".wma"
    ]
  },
  {
    "name": "application/x-ms-wmd",
    "fileTypes": [
      ".wmd"
    ]
  },
  {
    "name": "application/x-msmetafile",
    "fileTypes": [
      ".wmf"
    ]
  },
  {
    "name": "text/vnd.wap.wml",
    "fileTypes": [
      ".wml"
    ]
  },
  {
    "name": "application/vnd.wap.wmlc",
    "fileTypes": [
      ".wmlc"
    ]
  },
  {
    "name": "text/vnd.wap.wmlscript",
    "fileTypes": [
      ".wmls"
    ]
  },
  {
    "name": "application/vnd.wap.wmlscriptc",
    "fileTypes": [
      ".wmlsc"
    ]
  },
  {
    "name": "video/x-ms-wmv",
    "fileTypes": [
      ".wmv"
    ]
  },
  {
    "name": "video/x-ms-wmx",
    "fileTypes": [
      ".wmx"
    ]
  },
  {
    "name": "application/x-ms-wmz",
    "fileTypes": [
      ".wmz"
    ]
  },
  {
    "name": "application/vnd.wordperfect",
    "fileTypes": [
      ".wpd"
    ]
  },
  {
    "name": "application/vnd.ms-wpl",
    "fileTypes": [
      ".wpl"
    ]
  },
  {
    "name": "application/vnd.wqd",
    "fileTypes": [
      ".wqd"
    ]
  },
  {
    "name": "application/x-mswrite",
    "fileTypes": [
      ".wri"
    ]
  },
  {
    "name": "application/wsdl+xml",
    "fileTypes": [
      ".wsdl"
    ]
  },
  {
    "name": "application/wspolicy+xml",
    "fileTypes": [
      ".wspolicy"
    ]
  },
  {
    "name": "application/vnd.webturbo",
    "fileTypes": [
      ".wtb"
    ]
  },
  {
    "name": "video/x-ms-wvx",
    "fileTypes": [
      ".wvx"
    ]
  },
  {
    "name": "application/vnd.hzn-3d-crossword",
    "fileTypes": [
      ".x3d"
    ]
  },
  {
    "name": "application/x-silverlight-app",
    "fileTypes": [
      ".xap"
    ]
  },
  {
    "name": "application/vnd.xara",
    "fileTypes": [
      ".xar"
    ]
  },
  {
    "name": "application/x-ms-xbap",
    "fileTypes": [
      ".xbap"
    ]
  },
  {
    "name": "application/vnd.fujixerox.docuworks.binder",
    "fileTypes": [
      ".xbd"
    ]
  },
  {
    "name": "image/x-xbitmap",
    "fileTypes": [
      ".xbm"
    ]
  },
  {
    "name": "application/vnd.syncml.dm+xml",
    "fileTypes": [
      ".xdm"
    ]
  },
  {
    "name": "application/vnd.adobe.xdp+xml",
    "fileTypes": [
      ".xdp"
    ]
  },
  {
    "name": "application/vnd.fujixerox.docuworks",
    "fileTypes": [
      ".xdw"
    ]
  },
  {
    "name": "application/xenc+xml",
    "fileTypes": [
      ".xenc"
    ]
  },
  {
    "name": "application/patch-ops-error+xml",
    "fileTypes": [
      ".xer"
    ]
  },
  {
    "name": "application/vnd.adobe.xfdf",
    "fileTypes": [
      ".xfdf"
    ]
  },
  {
    "name": "application/vnd.xfdl",
    "fileTypes": [
      ".xfdl"
    ]
  },
  {
    "name": "application/xhtml+xml",
    "fileTypes": [
      ".xht",
      ".xhtml"
    ]
  },
  {
    "name": "image/vnd.xiff",
    "fileTypes": [
      ".xif"
    ]
  },
  {
    "name": "application/vnd.ms-excel",
    "fileTypes": [
      ".xla",
      ".xlb",
      ".xlc",
      ".xlm",
      ".xls",
      ".xlt",
      ".xlw"
    ]
  },
  {
    "name": "application/vnd.ms-excel.addin.macroenabled.12",
    "fileTypes": [
      ".xlam"
    ]
  },
  {
    "name": "application/vnd.ms-excel.sheet.binary.macroenabled.12",
    "fileTypes": [
      ".xlsb"
    ]
  },
  {
    "name": "application/vnd.ms-excel.sheet.macroenabled.12",
    "fileTypes": [
      ".xlsm"
    ]
  },
  {
    "name": "application/vnd.openxmlformats-officedocument.spreadsheetml.sheet",
    "fileTypes": [
      ".xlsx"
    ]
  },
  {
    "name": "application/vnd.ms-excel.template.macroenabled.12",
    "fileTypes": [
      ".xltm"
    ]
  },
  {
    "name": "application/vnd.openxmlformats-officedocument.spreadsheetml.template",
    "fileTypes": [
      ".xltx"
    ]
  },
  {
    "name": "application/xml",
    "fileTypes": [
      ".xml",
      ".xpdl",
      ".xsl"
    ]
  },
  {
    "name": "application/vnd.olpc-sugar",
    "fileTypes": [
      ".xo"
    ]
  },
  {
    "name": "application/xop+xml",
    "fileTypes": [
      ".xop"
    ]
  },
  {
    "name": "application/x-xpinstall",
    "fileTypes": [
      ".xpi"
    ]
  },
  {
    "name": "image/x-xpixmap",
    "fileTypes": [
      ".xpm"
    ]
  },
  {
    "name": "application/vnd.is-xpr",
    "fileTypes": [
      ".xpr"
    ]
  },
  {
    "name": "application/vnd.ms-xpsdocument",
    "fileTypes": [
      ".xps"
    ]
  },
  {
    "name": "application/vnd.intercon.formnet",
    "fileTypes": [
      ".xpw",
      ".xpx"
    ]
  },
  {
    "name": "application/xslt+xml",
    "fileTypes": [
      ".xslt"
    ]
  },
  {
    "name": "application/vnd.syncml+xml",
    "fileTypes": [
      ".xsm"
    ]
  },
  {
    "name": "application/xspf+xml",
    "fileTypes": [
      ".xspf"
    ]
  },
  {
    "name": "application/vnd.mozilla.xul+xml",
    "fileTypes": [
      ".xul"
    ]
  },
  {
    "name": "image/x-xwindowdump",
    "fileTypes": [
      ".xwd"
    ]
  },
  {
    "name": "chemical/x-xyz",
    "fileTypes": [
      ".xyz"
    ]
  },
  {
    "name": "application/vnd.zzazz.deck+xml",
    "fileTypes": [
      ".zaz"
    ]
  },
  {
    "name": "application/zip",
    "fileTypes": [
      ".zip"
    ]
  },
  {
    "name": "application/x-zip-compressed",
    "deprecated": true,
    "useInstead": "application/zip",
    "fileTypes": [
      ".zip"
    ]
  },
  {
    "name": "application/zip-compressed",
    "deprecated": true,
    "useInstead": "application/zip",
    "fileTypes": [
      ".zip"
    ]
  },
  {
    "name": "application/vnd.zul",
    "fileTypes": [
      ".zir",
      ".zirz"
    ]
  },
  {
    "name": "application/vnd.handheld-entertainment+xml",
    "fileTypes": [
      ".zmm"
    ]
  },
  {
    "name": "image/x-adobe-dng",
    "fileTypes": [
      ".dng"
    ]
  },
  {
    "name": "image/x-sony-arw",
    "fileTypes": [
      ".arw"
    ]
  },
  {
    "name": "image/x-canon-cr2",
    "fileTypes": [
      ".cr2"
    ]
  },
  {
    "name": "image/x-canon-crw",
    "fileTypes": [
      ".crw"
    ]
  },
  {
    "name": "image/x-kodak-dcr",
    "fileTypes": [
      ".dcr"
    ]
  },
  {
    "name": "image/x-epson-erf",
    "fileTypes": [
      ".erf"
    ]
  },
  {
    "name": "image/x-kodak-k25",
    "fileTypes": [
      ".k25"
    ]
  },
  {
    "name": "image/x-kodak-kdc",
    "fileTypes": [
      ".kdc"
    ]
  },
  {
    "name": "image/x-minolta-mrw",
    "fileTypes": [
      ".mrw"
    ]
  },
  {
    "name": "image/x-nikon-nef",
    "fileTypes": [
      ".nef"
    ]
  },
  {
    "name": "image/x-olympus-orf",
    "fileTypes": [
      ".orf"
    ]
  },
  {
    "name": "image/x-pentax-pef",
    "fileTypes": [
      ".pef",
      ".ptx"
    ]
  },
  {
    "name": "image/x-fuji-raf",
    "fileTypes": [
      ".raf"
    ]
  },
  {
    "name": "image/x-panasonic-raw",
    "fileTypes": [
      ".raw",
      ".rw2",
      ".rwl"
    ]
  },
  {
    "name": "audio/flac",
    "fileTypes": [
      ".flac"
    ]
  },
  {
    "name": "image/x-sony-sr2",
    "fileTypes": [
      ".sr2"
    ]
  },
  {
    "name": "image/x-sony-srf",
    "fileTypes": [
      ".srf"
    ]
  },
  {
    "name": "image/x-sigma-x3f",
    "fileTypes": [
      ".x3f"
    ]
  }
]